{
  "name": "Blut des Dolches (passiv)",
  "type": "zauber",
  "img": "systems/Ilaris/assets/images/skills/profan-skill.svg",
  "system": {
    "fertigkeiten": "Dolchzauber",
    "fertigkeit_ausgewaehlt": "auto",
    "text": "Du kannst wie mit dem Vorteil Verbotene Pforten Lebenskraft für deine Zauber nutzen (S. 73). Verfügst du bereits über Verbotene Pforten, stellt jede selbst zugefügt Wunde WS+8 AsP zur Verfügung. Überschüssige AsP verfallen.",
    "maechtig": "",
    "schwierigkeit": "",
    "modifikationen": "",
    "vorbereitung": "",
    "ziel": "",
    "reichweite": "",
    "wirkungsdauer": "",
    "kosten": "",
    "erlernen": "Dru 18; 40 EP",
    "pw": 0,
    "gruppe": 0,
    "typ": "zauber"
  },
  "effects": [],
  "folder": null,
  "sort": 0,
  "flags": {},
  "ownership": {
    "default": 0,
    "bRsoRPItEVb33T1L": 3
  },
  "_id": "HySTjUEIIogJpM3E",
  "_stats": {
    "compendiumSource": null,
    "duplicateSource": null,
    "coreVersion": "12.343",
    "systemId": "Ilaris",
    "systemVersion": "12.2.6",
    "createdTime": 1767873426605,
    "modifiedTime": 1767873426605,
    "lastModifiedBy": "bRsoRPItEVb33T1L"
  },
  "_key": "!items!HySTjUEIIogJpM3E"
}
