{
  "name": "Aktion Langsam (voll)",
  "type": "effect-item",
  "_id": "KIpKfTdGDMmGl3JH",
  "img": "icons/svg/item-bag.svg",
  "system": {
    "description": ""
  },
  "effects": [
    {
      "name": "INI-2",
      "origin": "Compendium.ilaris-alternative-actor-sheet.nenneke-aktionen.Item.KIpKfTdGDMmGl3JH",
      "disabled": false,
      "img": "icons/svg/aura.svg",
      "_id": "NDSIO6LNo7lxQyhN",
      "type": "base",
      "system": {},
      "changes": [
        {
          "key": "system.abgeleitete.ini",
          "mode": 2,
          "value": "-2",
          "priority": null
        }
      ],
      "duration": {
        "startTime": null,
        "seconds": null,
        "combat": null,
        "rounds": null,
        "turns": 1,
        "startRound": null,
        "startTurn": null
      },
      "description": "",
      "tint": "#ffffff",
      "transfer": true,
      "statuses": [],
      "sort": 0,
      "flags": {},
      "_stats": {
        "compendiumSource": null,
        "duplicateSource": null,
        "coreVersion": "12.343",
        "systemId": "Ilaris",
        "systemVersion": "12.2.6",
        "createdTime": 1767701216014,
        "modifiedTime": 1767701230942,
        "lastModifiedBy": "bRsoRPItEVb33T1L"
      },
      "_key": "!items.effects!KIpKfTdGDMmGl3JH.NDSIO6LNo7lxQyhN"
    }
  ],
  "folder": null,
  "sort": 0,
  "ownership": {
    "default": 0,
    "bRsoRPItEVb33T1L": 3
  },
  "flags": {},
  "_stats": {
    "compendiumSource": null,
    "duplicateSource": null,
    "coreVersion": "12.343",
    "systemId": "Ilaris",
    "systemVersion": "12.2.6",
    "createdTime": 1767700461416,
    "modifiedTime": 1767700461416,
    "lastModifiedBy": "bRsoRPItEVb33T1L"
  },
  "_key": "!items!KIpKfTdGDMmGl3JH"
}
